twikey/__init__.py
twikey/client.py
twikey/document.py
twikey/invoice.py
twikey/paylink.py
twikey/refund.py
twikey/transaction.py
twikey/webhook.py
twikey_api_python-0.2.3.dist-info/METADATA
twikey_api_python-0.2.3.dist-info/WHEEL
twikey_api_python-0.2.3.dist-info/top_level.txt
twikey_api_python-0.2.3.dist-info/RECORD
