Metadata-Version: 2.2
Name: twikey-api-python
Version: 0.2.3
Summary: Python interface with the Twikey api
Home-page: https://github.com/twikey/twikey-api-python
Author: Twikey
Author-email: support@twikey.com
License: MIT
Project-URL: Bug Tracker, https://github.com/twikey/twikey-api-python/issues
Project-URL: Source Code, https://github.com/twikey/twikey-api-python
Keywords: twikey api payments
Classifier: Development Status :: 5 - Production/Stable
Classifier: Intended Audience :: Developers
Classifier: License :: OSI Approved :: MIT License
Classifier: Operating System :: OS Independent
Classifier: Programming Language :: Python
Classifier: Programming Language :: Python :: 3
Classifier: Programming Language :: Python :: 3.6
Classifier: Programming Language :: Python :: 3.7
Classifier: Programming Language :: Python :: 3.8
Classifier: Programming Language :: Python :: 3.9
Classifier: Programming Language :: Python :: Implementation :: PyPy
Classifier: Topic :: Software Development :: Libraries :: Python Modules
Requires-Python: >=3.6
Requires-Dist: requests>=2.32; python_version >= "3.0"
Requires-Dist: requests[security]>=2.32; python_version < "3.0"
Dynamic: author
Dynamic: author-email
Dynamic: classifier
Dynamic: description
Dynamic: description-content-type
Dynamic: home-page
Dynamic: keywords
Dynamic: license
Dynamic: project-url
Dynamic: requires-dist
Dynamic: requires-python
Dynamic: summary
